LICENSE
MANIFEST.in
README
setup.py
doc/html/genindex.html
doc/html/index.html
doc/html/objects.inv
doc/html/py-modindex.html
doc/html/search.html
doc/html/searchindex.js
doc/html/_sources/index.txt
doc/html/_static/basic.css
doc/html/_static/default.css
doc/html/_static/doctools.js
doc/html/_static/file.png
doc/html/_static/jquery.js
doc/html/_static/minus.png
doc/html/_static/plus.png
doc/html/_static/pygments.css
doc/html/_static/searchtools.js
doc/html/_static/sidebar.js
doc/html/_static/underscore.js
nmevent/nmevent.py
nmevent/nmevent.egg-info/PKG-INFO
nmevent/nmevent.egg-info/SOURCES.txt
nmevent/nmevent.egg-info/dependency_links.txt
nmevent/nmevent.egg-info/top_level.txt
test/test_nmevent.py