Metadata-Version: 1.1
Name: nmevent
Version: 0.3
Summary: A simple C#-like implementation of the Observer design pattern.
Home-page: http://pypi.python.org/pypi/nmevent
Author: Jan Milík
Author-email: milikjan@fit.cvut.cz
License: Lesser General Public License v3
Keywords: library event observer pattern
Platform: UNKNOWN
Classifier: Development Status :: 3 - Alpha
Classifier: Intended Audience :: Developers
Classifier: License :: OSI Approved :: GNU Library or Lesser General Public License (LGPL)
Classifier: Natural Language :: English
Classifier: Operating System :: OS Independent
Classifier: Programming Language :: Python :: 2.6
Provides: nmevent
